aiconfigurator/__init__.py
aiconfigurator/main.py
aiconfigurator/cli/__init__.py
aiconfigurator/cli/example.yaml
aiconfigurator/cli/main.py
aiconfigurator/cli/report_and_save.py
aiconfigurator/cli/exps/b200_qwen3_32b.yaml
aiconfigurator/cli/exps/database_mode_comparison.yaml
aiconfigurator/cli/exps/deepseek_disagg_sglang.yaml
aiconfigurator/cli/exps/deepseek_wideep_trtllm.yaml
aiconfigurator/cli/exps/h200_qwen3_32b_multi_backends.yaml
aiconfigurator/cli/exps/hetero_disagg.yaml
aiconfigurator/cli/exps/qwen3_32b_disagg.yaml
aiconfigurator/cli/exps/qwen3_32b_disagg_pertensor.yaml
aiconfigurator/cli/exps/qwen3_32b_request_latency.yaml
aiconfigurator/eval/gpu.py
aiconfigurator/eval/main.py
aiconfigurator/eval/pipeline.py
aiconfigurator/eval/service.py
aiconfigurator/eval/utils.py
aiconfigurator/eval/benchmarks/__init__.py
aiconfigurator/eval/benchmarks/genai_perf_runner.py
aiconfigurator/eval/plots/__init__.py
aiconfigurator/eval/plots/pareto.py
aiconfigurator/eval/plots/timeseries.py
aiconfigurator/generator/__init__.py
aiconfigurator/generator/aggregators.py
aiconfigurator/generator/api.py
aiconfigurator/generator/artifacts.py
aiconfigurator/generator/main.py
aiconfigurator/generator/module_bridge.py
aiconfigurator/generator/utils.py
aiconfigurator/generator/config/backend_config_mapping.yaml
aiconfigurator/generator/config/deployment_config.yaml
aiconfigurator/generator/config/backend_templates/sglang/cli_args.0.5.1.post1.j2
aiconfigurator/generator/config/backend_templates/sglang/cli_args.0.5.3.post2.j2
aiconfigurator/generator/config/backend_templates/sglang/cli_args.0.5.4.post3.j2
aiconfigurator/generator/config/backend_templates/sglang/cli_args.j2
aiconfigurator/generator/config/backend_templates/sglang/k8s_deploy.yaml.j2
aiconfigurator/generator/config/backend_templates/sglang/run.sh.j2
aiconfigurator/generator/config/backend_templates/trtllm/extra_engine_args.0.20.0.yaml.j2
aiconfigurator/generator/config/backend_templates/trtllm/extra_engine_args.1.0.0.yaml.j2
aiconfigurator-0.5.0.post0.dist-info/licenses/LICENSE
aiconfigurator-0.5.0.post0.dist-info/METADATA
aiconfigurator-0.5.0.post0.dist-info/WHEEL
aiconfigurator-0.5.0.post0.dist-info/entry_points.txt
aiconfigurator-0.5.0.post0.dist-info/top_level.txt
aiconfigurator-0.5.0.post0.dist-info/RECORD
