Metadata-Version: 2.4
Name: aiconfigurator
Version: 0.5.0.post0
Summary: aiconfigurator: automatic disaggregated serving offline configuration
Author-email: "NVIDIA Inc." <sw-dl-dynamo@nvidia.com>
License-Expression: Apache-2.0
Project-URL: GitHub, https://github.com/ai-dynamo/aiconfigurator
Project-URL: Repository, https://github.com/ai-dynamo/aiconfigurator.git
Keywords: decode,distributed,dynamo,gpu,inference,llm,nvidia,prefill
Classifier: Development Status :: 4 - Beta
Classifier: Intended Audience :: Developers
Classifier: Intended Audience :: Science/Research
Classifier: Intended Audience :: Information Technology
Classifier: Programming Language :: Python :: 3
Classifier: Programming Language :: Python :: 3.9
Classifier: Programming Language :: Python :: 3.10
Classifier: Programming Language :: Python :: 3.11
Classifier: Programming Language :: Python :: 3.12
Classifier: Topic :: Scientific/Engineering
Classifier: Topic :: Scientific/Engineering :: Artificial Intelligence
Requires-Python: >=3.9
License-File: LICENSE
Requires-Dist: uv
Requires-Dist: fastapi>=0.115.12
Requires-Dist: jinja2>=3.1.0
Requires-Dist: matplotlib>=3.9.4
Requires-Dist: numpy~=1.26.4
Requires-Dist: orjson>=3.10.16
Requires-Dist: pandas>=2.2.3
Requires-Dist: plotext>=5.3.2
Requires-Dist: plotly>=6.0.1
Requires-Dist: prettytable>=3.16.0
Requires-Dist: pyyaml>=6.0
Requires-Dist: scipy>=1.13.1
Requires-Dist: tqdm>=4.0.0
Requires-Dist: uvicorn>=0.34.2
Requires-Dist: bokeh
Requires-Dist: nvidia-ml-py
Requires-Dist: munch>=4.0.0
Provides-Extra: dev
Requires-Dist: ruff==0.14.1; extra == "dev"
Requires-Dist: pre-commit==4.3.0; extra == "dev"
Requires-Dist: pytest>=8.3.5; extra == "dev"
Requires-Dist: pytest-asyncio>=0.26.0; extra == "dev"
Requires-Dist: pytest-cov>=6.1.1; extra == "dev"
Requires-Dist: pytest-md-report==0.7.0; extra == "dev"
Requires-Dist: pytest-mock>=3.14.0; extra == "dev"
Requires-Dist: pytest-split>=0.10.0; extra == "dev"
Requires-Dist: pytest-timeout>=2.3.1; extra == "dev"
Requires-Dist: pytest-xdist==3.8.0; extra == "dev"
Provides-Extra: webapp
Requires-Dist: gradio==5.47.1; extra == "webapp"
Dynamic: license-file
